sum/main.py
sum/sum_core.py
sum/pyarmor_runtime_000000/__init__.py
sum/pyarmor_runtime_000000/pyarmor_runtime.pyd
bcd_sum_demo-0.1.1.dist-info/METADATA
bcd_sum_demo-0.1.1.dist-info/WHEEL
bcd_sum_demo-0.1.1.dist-info/top_level.txt
bcd_sum_demo-0.1.1.dist-info/RECORD
