Metadata-Version: 2.4
Name: bcd-sum-demo
Version: 0.1.1
Summary: Obfuscated sum demo
Requires-Python: >=3.12
